web2json/__init__.py
web2json/ai_extractor.py
web2json/cli.py
web2json/crawler.py
web2json/pipeline.py
web2json/postprocessor.py
web2json/preprocessor.py
web2json-0.0.13.dist-info/licenses/LICENSE
web2json-0.0.13.dist-info/METADATA
web2json-0.0.13.dist-info/WHEEL
web2json-0.0.13.dist-info/entry_points.txt
web2json-0.0.13.dist-info/top_level.txt
web2json-0.0.13.dist-info/RECORD
