Metadata-Version: 2.4
Name: web2json
Version: 0.0.13
Summary: Convert web content into JSON using local Ollama LLM
Author-email: NOAA Global Systems Laboratory <eric.j.hackathorn@noaa.gov>
License: MIT
Project-URL: Homepage, https://github.com/NOAA-GSL/web2json
Project-URL: Issues, https://github.com/NOAA-GSL/web2json/issues
Classifier: Programming Language :: Python :: 3
Classifier: Operating System :: OS Independent
Requires-Python: >=3.10
License-File: LICENSE
Requires-Dist: pandas>=1.3.0
Requires-Dist: pydantic>=1.10.0
Requires-Dist: python-dotenv>=0.21.0
Requires-Dist: beautifulsoup4>=4.9.0
Requires-Dist: requests>=2.25.0
Requires-Dist: json_repair>=0.46.0
Dynamic: license-file
